greetings/__init__.py
greetings/greetings.py
greetings_Shiloh6-1.1.0.dist-info/LICENSE
greetings_Shiloh6-1.1.0.dist-info/METADATA
greetings_Shiloh6-1.1.0.dist-info/WHEEL
greetings_Shiloh6-1.1.0.dist-info/top_level.txt
greetings_Shiloh6-1.1.0.dist-info/RECORD
